{
  "slug": "al-ettifaq",
  "teamId": 2938,
  "upcoming": [
    {
      "id": "756174",
      "date": "2026-05-04T18:00Z",
      "timestamp": 1777917600,
      "status": "NS",
      "statusLong": "Scheduled",
      "venue": "Al Ettifaq Club Stadium",
      "city": "Dammam",
      "home": {
        "id": "8363",
        "slug": "al-ettifaq",
        "name": "الاتفاق",
        "logo": "https://media.api-sports.io/football/teams/2938.png",
        "winner": null
      },
      "away": {
        "id": "22023",
        "slug": null,
        "name": "Al Najma",
        "logo": "",
        "winner": null
      },
      "goals": {
        "home": null,
        "away": null
      },
      "league": {
        "name": "Saudi Pro League",
        "round": ""
      },
      "completed": false
    },
    {
      "id": "756189",
      "date": "2026-05-09T15:55Z",
      "timestamp": 1778342100,
      "status": "NS",
      "statusLong": "Scheduled",
      "venue": "Prince Mohammed Bin Fahd Stadium",
      "city": "Dammam",
      "home": {
        "id": "21829",
        "slug": null,
        "name": "Al Khaleej",
        "logo": "",
        "winner": null
      },
      "away": {
        "id": "8363",
        "slug": "al-ettifaq",
        "name": "الاتفاق",
        "logo": "https://media.api-sports.io/football/teams/2938.png",
        "winner": null
      },
      "goals": {
        "home": null,
        "away": null
      },
      "league": {
        "name": "Saudi Pro League",
        "round": ""
      },
      "completed": false
    },
    {
      "id": "756192",
      "date": "2026-05-14T18:00Z",
      "timestamp": 1778781600,
      "status": "NS",
      "statusLong": "Scheduled",
      "venue": "Al Ettifaq Club Stadium",
      "city": "Dammam",
      "home": {
        "id": "8363",
        "slug": "al-ettifaq",
        "name": "الاتفاق",
        "logo": "https://media.api-sports.io/football/teams/2938.png",
        "winner": null
      },
      "away": {
        "id": "2276",
        "slug": "al-ittihad",
        "name": "الاتحاد",
        "logo": "https://media.api-sports.io/football/teams/2933.png",
        "winner": null
      },
      "goals": {
        "home": null,
        "away": null
      },
      "league": {
        "name": "Saudi Pro League",
        "round": ""
      },
      "completed": false
    },
    {
      "id": "756201",
      "date": "2026-05-20T18:00Z",
      "timestamp": 1779300000,
      "status": "NS",
      "statusLong": "Scheduled",
      "venue": "King Khalid Sport City Stadium",
      "city": "Tabuk",
      "home": {
        "id": "130899",
        "slug": null,
        "name": "Neom SC",
        "logo": "",
        "winner": null
      },
      "away": {
        "id": "8363",
        "slug": "al-ettifaq",
        "name": "الاتفاق",
        "logo": "https://media.api-sports.io/football/teams/2938.png",
        "winner": null
      },
      "goals": {
        "home": null,
        "away": null
      },
      "league": {
        "name": "Saudi Pro League",
        "round": ""
      },
      "completed": false
    }
  ],
  "past": [
    {
      "id": "756165",
      "date": "2026-04-30T16:00Z",
      "timestamp": 1777564800,
      "status": "FT",
      "statusLong": "Full Time",
      "venue": "Prince Hathloul Bin Abdulaziz Sport City Stadium",
      "city": "Najran",
      "home": {
        "id": "21966",
        "slug": "al-okhdood",
        "name": "الأخدود",
        "logo": "https://media.api-sports.io/football/teams/7802.png",
        "winner": false
      },
      "away": {
        "id": "8363",
        "slug": "al-ettifaq",
        "name": "الاتفاق",
        "logo": "https://media.api-sports.io/football/teams/2938.png",
        "winner": true
      },
      "goals": {
        "home": 1,
        "away": 3
      },
      "league": {
        "name": "Saudi Pro League",
        "round": ""
      },
      "completed": true
    },
    {
      "id": "756160",
      "date": "2026-04-15T18:00Z",
      "timestamp": 1776276000,
      "status": "FT",
      "statusLong": "Full Time",
      "venue": "Al-Awwal Park",
      "city": "King Fahd International Stadium",
      "home": {
        "id": "817",
        "slug": "al-nassr",
        "name": "النصر",
        "logo": "https://media.api-sports.io/football/teams/2939.png",
        "winner": true
      },
      "away": {
        "id": "8363",
        "slug": "al-ettifaq",
        "name": "الاتفاق",
        "logo": "https://media.api-sports.io/football/teams/2938.png",
        "winner": false
      },
      "goals": {
        "home": 1,
        "away": 0
      },
      "league": {
        "name": "Saudi Pro League",
        "round": ""
      },
      "completed": true
    },
    {
      "id": "756152",
      "date": "2026-04-09T18:00Z",
      "timestamp": 1775757600,
      "status": "FT",
      "statusLong": "Full Time",
      "venue": "Al Ettifaq Club Stadium",
      "city": "Dammam",
      "home": {
        "id": "8363",
        "slug": "al-ettifaq",
        "name": "الاتفاق",
        "logo": "https://media.api-sports.io/football/teams/2938.png",
        "winner": false
      },
      "away": {
        "id": "21965",
        "slug": "al-riyadh",
        "name": "الرياض",
        "logo": "https://media.api-sports.io/football/teams/7800.png",
        "winner": true
      },
      "goals": {
        "home": 2,
        "away": 3
      },
      "league": {
        "name": "Saudi Pro League",
        "round": ""
      },
      "completed": true
    },
    {
      "id": "756146",
      "date": "2026-04-05T18:00Z",
      "timestamp": 1775412000,
      "status": "FT",
      "statusLong": "Full Time",
      "venue": "Al Ettifaq Club Stadium",
      "city": "Dammam",
      "home": {
        "id": "8363",
        "slug": "al-ettifaq",
        "name": "الاتفاق",
        "logo": "https://media.api-sports.io/football/teams/2938.png",
        "winner": true
      },
      "away": {
        "id": "22022",
        "slug": "al-qadsiah",
        "name": "القادسية",
        "logo": "https://media.api-sports.io/football/teams/2934.png",
        "winner": false
      },
      "goals": {
        "home": 3,
        "away": 2
      },
      "league": {
        "name": "Saudi Pro League",
        "round": ""
      },
      "completed": true
    }
  ],
  "fetchedAt": "2026-05-03T23:54:09.119Z"
}