{
  "slug": "al-hilal",
  "teamId": 0,
  "upcoming": [
    {
      "id": "756154",
      "date": "2026-05-05T18:00Z",
      "timestamp": 1778004000,
      "status": "NS",
      "statusLong": "Scheduled",
      "venue": "Prince Mohammed Bin Fahd Stadium",
      "city": "Dammam",
      "home": {
        "id": "21829",
        "slug": null,
        "name": "Al Khaleej",
        "logo": "",
        "winner": null
      },
      "away": {
        "id": "929",
        "slug": "al-hilal",
        "name": "الهلال",
        "logo": "https://media.api-sports.io/football/teams/2932.png",
        "winner": null
      },
      "goals": {
        "home": null,
        "away": null
      },
      "league": {
        "name": "Saudi Pro League",
        "round": ""
      },
      "completed": false
    },
    {
      "id": "756183",
      "date": "2026-05-12T18:00Z",
      "timestamp": 1778608800,
      "status": "NS",
      "statusLong": "Scheduled",
      "venue": "Al-Awwal Park",
      "city": "King Fahd International Stadium",
      "home": {
        "id": "817",
        "slug": "al-nassr",
        "name": "النصر",
        "logo": "https://media.api-sports.io/football/teams/2939.png",
        "winner": null
      },
      "away": {
        "id": "929",
        "slug": "al-hilal",
        "name": "الهلال",
        "logo": "https://media.api-sports.io/football/teams/2932.png",
        "winner": null
      },
      "goals": {
        "home": null,
        "away": null
      },
      "league": {
        "name": "Saudi Pro League",
        "round": ""
      },
      "completed": false
    },
    {
      "id": "756193",
      "date": "2026-05-16T16:05Z",
      "timestamp": 1778947500,
      "status": "NS",
      "statusLong": "Scheduled",
      "venue": "Kingdom Arena",
      "city": "King Fahd International Stadium",
      "home": {
        "id": "929",
        "slug": "al-hilal",
        "name": "الهلال",
        "logo": "https://media.api-sports.io/football/teams/2932.png",
        "winner": null
      },
      "away": {
        "id": "130899",
        "slug": null,
        "name": "Neom SC",
        "logo": "",
        "winner": null
      },
      "goals": {
        "home": null,
        "away": null
      },
      "league": {
        "name": "Saudi Pro League",
        "round": ""
      },
      "completed": false
    },
    {
      "id": "756204",
      "date": "2026-05-20T18:00Z",
      "timestamp": 1779300000,
      "status": "NS",
      "statusLong": "Scheduled",
      "venue": "Al Majma'a Sport City Stadium",
      "city": "Al Majma'ah",
      "home": {
        "id": "21827",
        "slug": "al-fayha",
        "name": "الفيحاء",
        "logo": "https://media.api-sports.io/football/teams/7795.png",
        "winner": null
      },
      "away": {
        "id": "929",
        "slug": "al-hilal",
        "name": "الهلال",
        "logo": "https://media.api-sports.io/football/teams/2932.png",
        "winner": null
      },
      "goals": {
        "home": null,
        "away": null
      },
      "league": {
        "name": "Saudi Pro League",
        "round": ""
      },
      "completed": false
    }
  ],
  "past": [
    {
      "id": "756180",
      "date": "2026-05-02T18:00Z",
      "timestamp": 1777744800,
      "status": "FT",
      "statusLong": "Full Time",
      "venue": "Al-Hazm Club Stadium",
      "city": "Al-Rass",
      "home": {
        "id": "21964",
        "slug": "al-hazm",
        "name": "الحزم",
        "logo": "https://media.api-sports.io/football/teams/7801.png",
        "winner": false
      },
      "away": {
        "id": "929",
        "slug": "al-hilal",
        "name": "الهلال",
        "logo": "https://media.api-sports.io/football/teams/2932.png",
        "winner": true
      },
      "goals": {
        "home": 0,
        "away": 3
      },
      "league": {
        "name": "Saudi Pro League",
        "round": ""
      },
      "completed": true
    },
    {
      "id": "756168",
      "date": "2026-04-28T18:00Z",
      "timestamp": 1777399200,
      "status": "FT",
      "statusLong": "Full Time",
      "venue": "Kingdom Arena",
      "city": "King Fahd International Stadium",
      "home": {
        "id": "929",
        "slug": "al-hilal",
        "name": "الهلال",
        "logo": "https://media.api-sports.io/football/teams/2932.png",
        "winner": true
      },
      "away": {
        "id": "21828",
        "slug": "damac",
        "name": "ضمك",
        "logo": "https://media.api-sports.io/football/teams/7796.png",
        "winner": false
      },
      "goals": {
        "home": 1,
        "away": 0
      },
      "league": {
        "name": "Saudi Pro League",
        "round": ""
      },
      "completed": true
    },
    {
      "id": "756158",
      "date": "2026-04-08T18:00Z",
      "timestamp": 1775671200,
      "status": "FT",
      "statusLong": "Full Time",
      "venue": "Kingdom Arena",
      "city": "King Fahd International Stadium",
      "home": {
        "id": "929",
        "slug": "al-hilal",
        "name": "الهلال",
        "logo": "https://media.api-sports.io/football/teams/2932.png",
        "winner": true
      },
      "away": {
        "id": "22028",
        "slug": "al-kholood",
        "name": "الخلود",
        "logo": "https://media.api-sports.io/football/teams/2941.png",
        "winner": false
      },
      "goals": {
        "home": 6,
        "away": 0
      },
      "league": {
        "name": "Saudi Pro League",
        "round": ""
      },
      "completed": true
    },
    {
      "id": "756145",
      "date": "2026-04-04T18:00Z",
      "timestamp": 1775325600,
      "status": "FT",
      "statusLong": "Full Time",
      "venue": "Kingdom Arena",
      "city": "King Fahd International Stadium",
      "home": {
        "id": "929",
        "slug": "al-hilal",
        "name": "الهلال",
        "logo": "https://media.api-sports.io/football/teams/2932.png",
        "winner": false
      },
      "away": {
        "id": "18459",
        "slug": null,
        "name": "Al Taawoun",
        "logo": "",
        "winner": false
      },
      "goals": {
        "home": 2,
        "away": 2
      },
      "league": {
        "name": "Saudi Pro League",
        "round": ""
      },
      "completed": true
    }
  ],
  "fetchedAt": "2026-05-04T18:24:27.850Z"
}