{
  "runAt": "2026-06-21T09:02:01.339Z",
  "totalArticles": 2118,
  "issuesFound": 12,
  "headChecked": 2,
  "changed": true,
  "issues": [
    {
      "slug": "ft-1gobjd",
      "type": "MISSING_FILE",
      "detail": "/generated/ft-1gobjd.png"
    },
    {
      "slug": "ft-11mg52",
      "type": "MISSING_FILE",
      "detail": "/generated/ft-11mg52.png"
    },
    {
      "slug": "ft-1l8dqk",
      "type": "MISSING_FILE",
      "detail": "/generated/ft-1l8dqk.png"
    },
    {
      "slug": "ft-17m4x1",
      "type": "MISSING_FILE",
      "detail": "/generated/ft-17m4x1.png"
    },
    {
      "slug": "ft-oi5cmv",
      "type": "MISSING_FILE",
      "detail": "/generated/ft-oi5cmv.png"
    },
    {
      "slug": "ft-fr0dfd",
      "type": "MISSING_FILE",
      "detail": "/generated/ft-fr0dfd.png"
    },
    {
      "slug": "ft-15ztrw",
      "type": "MISSING_FILE",
      "detail": "/generated/ft-15ztrw.png"
    },
    {
      "slug": "ft-qu3sav",
      "type": "MISSING_FILE",
      "detail": "/generated/ft-qu3sav.png"
    },
    {
      "slug": "bball-187bz1-1782020814077",
      "type": "MISSING_FILE",
      "detail": "/generated/bball-187bz1-1782020814077.png"
    },
    {
      "slug": "tennis-yiyxck-1782020991358",
      "type": "MISSING_FILE",
      "detail": "/generated/tennis-yiyxck-1782020991358.png"
    },
    {
      "slug": "padel-cyhnw0-1782021063933",
      "type": "MISSING_FILE",
      "detail": "/generated/padel-cyhnw0-1782021063933.png"
    },
    {
      "slug": "tennis-rlrc2q-1782020886612",
      "type": "MISSING_FILE",
      "detail": "/generated/tennis-rlrc2q-1782020886612.png"
    }
  ]
}