{
  "runAt": "2026-06-07T02:13:29.244Z",
  "totalArticles": 1075,
  "issuesFound": 14,
  "headChecked": 1,
  "changed": true,
  "issues": [
    {
      "slug": "ft-1yqlq3",
      "type": "MISSING_FILE",
      "detail": "/generated/ft-1yqlq3.png"
    },
    {
      "slug": "ft-19e73m",
      "type": "MISSING_FILE",
      "detail": "/generated/ft-19e73m.png"
    },
    {
      "slug": "ft-10gssr",
      "type": "MISSING_FILE",
      "detail": "/generated/ft-10gssr.png"
    },
    {
      "slug": "ft-r104c4",
      "type": "MISSING_FILE",
      "detail": "/generated/ft-r104c4.png"
    },
    {
      "slug": "ft-17zb20",
      "type": "MISSING_FILE",
      "detail": "/generated/ft-17zb20.png"
    },
    {
      "slug": "ft-7u3afs",
      "type": "MISSING_FILE",
      "detail": "/generated/ft-7u3afs.png"
    },
    {
      "slug": "ft-1sad2i",
      "type": "MISSING_FILE",
      "detail": "/generated/ft-1sad2i.png"
    },
    {
      "slug": "ft-1fsoyy",
      "type": "MISSING_FILE",
      "detail": "/generated/ft-1fsoyy.png"
    },
    {
      "slug": "ft-j6uik3",
      "type": "MISSING_FILE",
      "detail": "/generated/ft-j6uik3.png"
    },
    {
      "slug": "ft-1og9u3",
      "type": "MISSING_FILE",
      "detail": "/generated/ft-1og9u3.png"
    },
    {
      "slug": "ft-x1bsct",
      "type": "MISSING_FILE",
      "detail": "/generated/ft-x1bsct.png"
    },
    {
      "slug": "bball-1ftao6",
      "type": "MISSING_FILE",
      "detail": "/generated/bball-1ftao6.png"
    },
    {
      "slug": "bball-s2msul",
      "type": "MISSING_FILE",
      "detail": "/generated/bball-s2msul.png"
    },
    {
      "slug": "tennis-rlrc2q-1780786684328",
      "type": "MISSING_FILE",
      "detail": "/generated/tennis-rlrc2q-1780786684328.png"
    }
  ]
}